fundi/__init__.py
fundi/configurable.py
fundi/debug.py
fundi/exceptions.py
fundi/from_.py
fundi/from_.pyi
fundi/hooks.py
fundi/inject.py
fundi/inject.pyi
fundi/logging.py
fundi/py.typed
fundi/resolve.py
fundi/scan.py
fundi/side_effects.py
fundi/types.py
fundi/util.py
fundi/virtual_context.py
fundi-1.5.0.dist-info/licenses/LICENSE
fundi-1.5.0.dist-info/licenses/LICENSE.md
fundi-1.5.0.dist-info/METADATA
fundi-1.5.0.dist-info/WHEEL
fundi-1.5.0.dist-info/top_level.txt
fundi-1.5.0.dist-info/RECORD
