Metadata-Version: 2.4
Name: fundi
Version: 1.5.0
Summary: Dependency injection library
Author-email: Kuyugama <mail.kuyugama@gmail.com>
Project-URL: homepage, https://github.com/KuyuCode/fundi
Classifier: Programming Language :: Python :: 3
Requires-Python: >=3.10
License-File: LICENSE
License-File: LICENSE.md
Requires-Dist: typing-extensions>=4.13.0
Dynamic: license-file
